[
  {
    "timestamp": "2026-04-01T02:38:00+06:00",
    "method": "GET",
    "url": "/admin/login",
    "src_ip": "185.220.101.34",
    "status_code": 403,
    "user_agent": "Mozilla/5.0 (compatible; MSIE 10.0; Windows NT 6.1)",
    "response_size": 0,
    "duration_ms": 0
  },
  {
    "timestamp": "2026-04-01T02:39:00+06:00",
    "method": "GET",
    "url": "/api/v1/users",
    "src_ip": "185.220.101.34",
    "status_code": 401,
    "user_agent": "Mozilla/5.0 (compatible; MSIE 10.0; Windows NT 6.1)",
    "response_size": 0,
    "duration_ms": 0
  }
]