{
  "scenario": "13",
  "findings": [
    {
      "type": "cross_source_activity",
      "event_ids": [
        "evt_s13_001",
        "evt_s13_004",
        "evt_s13_005",
        "evt_s13_008",
        "evt_s13_009",
        "evt_s13_012",
        "evt_s13_013",
        "evt_s13_016",
        "evt_s13_017",
        "evt_s13_020",
        "evt_s13_021",
        "evt_s13_024",
        "evt_s13_025",
        "evt_s13_028",
        "evt_s13_002",
        "evt_s13_003",
        "evt_s13_006",
        "evt_s13_007",
        "evt_s13_010",
        "evt_s13_011",
        "evt_s13_014",
        "evt_s13_015",
        "evt_s13_018",
        "evt_s13_019",
        "evt_s13_022",
        "evt_s13_023",
        "evt_s13_026",
        "evt_s13_027"
      ],
      "description": "user_03 has activity across 2 source types: auth, file_access",
      "severity": "info"
    }
  ],
  "finding_count": 1,
  "severity_summary": {
    "info": 1
  }
}